Metadata-Version: 2.1
Name: multiploit
Version: 1.1.2.3
Summary: A python multi-purpose package
Home-page: https://yeetedwin.is-a.dev/multiploit
Author: YEETEDWIN
Author-email: yeetedwin@protonmail.com
License: MIT
Download-URL: https://yeetedwin.is-a.dev/multiploit/installing.html
Project-URL: Source Code, https://github.com/YEETEDWIN/multiploit
Project-URL: Documentation, https://yeetedwin.gitbook.io/multiploit/
Project-URL: Installation, https://yeetedwin.gitbook.io/multiploit/
Project-URL: Bug Tracker, https://github.com/YEETEDWIN/multiploit/issues
Keywords: multi-purpose multi simple one easier multiploit
Platform: any
Classifier: Development Status :: 1 - Planning
Classifier: Intended Audience :: Developers
Classifier: Intended Audience :: Education
Classifier: License :: OSI Approved :: MIT License
Classifier: Programming Language :: Python
Classifier: Programming Language :: Python :: 3.8
Classifier: Programming Language :: Python :: 3.9
Classifier: Natural Language :: English
Classifier: Topic :: Software Development
Classifier: Topic :: Education :: Testing
